Metadata-Version: 2.1
Name: pulumi-auto-deploy
Version: 0.0.4
Summary: UNKNOWN
Home-page: UNKNOWN
License: UNKNOWN
Platform: UNKNOWN
Requires-Python: >=3.7
